ocpsvg/__init__.py
ocpsvg/hlr.py
ocpsvg/ocp.py
ocpsvg/svg.py
ocpsvg-0.6.0.dist-info/licenses/LICENSE
ocpsvg-0.6.0.dist-info/METADATA
ocpsvg-0.6.0.dist-info/WHEEL
ocpsvg-0.6.0.dist-info/top_level.txt
ocpsvg-0.6.0.dist-info/RECORD
