Metadata-Version: 2.4
Name: ocpsvg
Version: 0.6.0
Requires-Python: >=3.10
License-File: LICENSE
Requires-Dist: cadquery_ocp_proxy<8.0,>=7.9
Requires-Dist: svgelements<2,>=1.9.1
Provides-Extra: dev
Requires-Dist: cadquery_ocp_novtk<8.0,>=7.9; extra == "dev"
Requires-Dist: pytest; extra == "dev"
Requires-Dist: coverage; extra == "dev"
Requires-Dist: mypy; extra == "dev"
Requires-Dist: ruff; extra == "dev"
Dynamic: license-file
